pytest_timeassert_ethan.py
pytest_timeassert_ethan-1.9.dist-info/LICENSE
pytest_timeassert_ethan-1.9.dist-info/METADATA
pytest_timeassert_ethan-1.9.dist-info/WHEEL
pytest_timeassert_ethan-1.9.dist-info/entry_points.txt
pytest_timeassert_ethan-1.9.dist-info/top_level.txt
pytest_timeassert_ethan-1.9.dist-info/RECORD
